scipdf/__init__.py
scipdf/features/__init__.py
scipdf/features/text_utils.py
scipdf/pdf/__init__.py
scipdf/pdf/parse_pdf.py
scipdf_parser-0.52.data/scripts/serve_grobid.sh
scipdf_parser-0.52.dist-info/LICENSE.txt
scipdf_parser-0.52.dist-info/METADATA
scipdf_parser-0.52.dist-info/WHEEL
scipdf_parser-0.52.dist-info/top_level.txt
scipdf_parser-0.52.dist-info/RECORD
