Metadata-Version: 2.1
Name: scipdf-parser
Version: 0.52
Summary: Python parser for scientific PDF based on GROBID.
Home-page: https://github.com/titipata/scipdf_parser
Author: Titipat Achakulvisut
Author-email: my.titipat@gmail.com
License: (c) MIT License 2019 Titipat Achakulvisut
Keywords: PDF parser,GROBID,Python PDF parser
Classifier: Programming Language :: Python :: 3
Classifier: License :: OSI Approved :: MIT License
Classifier: Operating System :: OS Independent
License-File: LICENSE.txt
Requires-Dist: lxml
Requires-Dist: requests
Requires-Dist: spacy
Requires-Dist: pandas
Requires-Dist: textstat
